basilisp/__init__.py
basilisp/cli.py
basilisp/contrib/__init__.py
basilisp/contrib/bencode.lpy
basilisp/contrib/nrepl_server.lpy
basilisp/contrib/pytest/__init__.py
basilisp/contrib/pytest/testrunner.py
basilisp/contrib/sphinx/__init__.py
basilisp/contrib/sphinx/autodoc.py
basilisp/contrib/sphinx/domain.py
basilisp/contrib/sphinx/linkcode.py
basilisp/core/protocols.lpy
basilisp/core.lpy
basilisp/data.lpy
basilisp/edn.lpy
basilisp/importer.py
basilisp/io.lpy
basilisp/json.lpy
basilisp/lang/__init__.py
basilisp/lang/atom.py
basilisp/lang/compiler/__init__.py
basilisp/lang/compiler/analyzer.py
basilisp/lang/compiler/constants.py
basilisp/lang/compiler/exception.py
basilisp/lang/compiler/generator.py
basilisp/lang/compiler/nodes.py
basilisp/lang/compiler/optimizer.py
basilisp/lang/compiler/utils.py
basilisp/lang/delay.py
basilisp/lang/exception.py
basilisp/lang/futures.py
basilisp/lang/interfaces.py
basilisp/lang/keyword.py
basilisp/lang/list.py
basilisp/lang/map.py
basilisp/lang/multifn.py
basilisp/lang/numbers.py
basilisp/lang/obj.py
basilisp/lang/promise.py
basilisp/lang/queue.py
basilisp/lang/reader.py
basilisp/lang/reduced.py
basilisp/lang/reference.py
basilisp/lang/runtime.py
basilisp/lang/seq.py
basilisp/lang/set.py
basilisp/lang/source.py
basilisp/lang/symbol.py
basilisp/lang/tagged.py
basilisp/lang/typing.py
basilisp/lang/util.py
basilisp/lang/vector.py
basilisp/lang/volatile.py
basilisp/logconfig.py
basilisp/main.py
basilisp/pprint.lpy
basilisp/process.lpy
basilisp/prompt.py
basilisp/repl.lpy
basilisp/set.lpy
basilisp/shell.lpy
basilisp/sitecustomize.py
basilisp/stacktrace.lpy
basilisp/string.lpy
basilisp/template.lpy
basilisp/test/fixtures.lpy
basilisp/test.lpy
basilisp/url.lpy
basilisp/util.py
basilisp/walk.lpy
basilisp-0.5.0.dist-info/METADATA
basilisp-0.5.0.dist-info/WHEEL
basilisp-0.5.0.dist-info/entry_points.txt
basilisp-0.5.0.dist-info/licenses/LICENSE
basilisp-0.5.0.dist-info/RECORD
