Metadata-Version: 2.4
Name: basilisp
Version: 0.5.0
Summary: A Clojure-like lisp written for Python
License-Expression: EPL-1.0
License-File: LICENSE
Author: Christopher Rink
Author-email: chris@crink.dev
Requires-Python: >=3.10
Classifier: Development Status :: 4 - Beta
Classifier: Intended Audience :: Developers
Classifier: Programming Language :: Python
Classifier: Programming Language :: Python :: 3
Classifier: Programming Language :: Python :: 3.10
Classifier: Programming Language :: Python :: 3.11
Classifier: Programming Language :: Python :: 3.12
Classifier: Programming Language :: Python :: 3.13
Classifier: Programming Language :: Python :: 3.14
Classifier: Programming Language :: Python :: Implementation :: CPython
Classifier: Programming Language :: Python :: Implementation :: PyPy
Classifier: Topic :: Software Development :: Compilers
Provides-Extra: pygments
Provides-Extra: pytest
Requires-Dist: attrs (>=22.2.0)
Requires-Dist: immutables (>=0.20,<1.0.0)
Requires-Dist: prompt-toolkit (>=3.0.0,<4.0.0)
Requires-Dist: pygments (>=2.9.0,<3.0.0) ; extra == "pygments"
Requires-Dist: pyrsistent (>=0.18.0,<1.0.0)
Requires-Dist: pytest (>=7.0.0,<9.0.0) ; extra == "pytest"
Requires-Dist: typing-extensions (>=4.7.0,<5.0.0)
